bookcase/__init__.py
bookcase/main.py
bookcase/utils.py
bookcase/tests/__init__.py
bookcase/tests/conftest.py
bookcase/tests/test_add.py
bookcase/tests/test_s3dbm.py
bookcase-0.0.0.dist-info/METADATA
bookcase-0.0.0.dist-info/WHEEL
bookcase-0.0.0.dist-info/licenses/LICENSE
bookcase-0.0.0.dist-info/RECORD
