Metadata-Version: 2.3
Name: bookcase
Version: 0.0.0
Summary: Organise all your data in key/value books and sync them with S3.
Project-URL: Documentation, https://mullenkamp.github.io/bookcase/
Project-URL: Source, https://github.com/mullenkamp/bookcase
Author-email: bookcase <mullenkamp1@gmail.com>
License-File: LICENSE
Classifier: Programming Language :: Python :: 3 :: Only
Requires-Python: >=3.10
Requires-Dist: booklet
Requires-Dist: orjson
Requires-Dist: s3func
Requires-Dist: urllib3
Requires-Dist: zstandard
